aleph_superfluid-0.3.dist-info/licenses/LICENSE.txt
superfluid/__init__.py
superfluid/src/__init__.py
superfluid/src/abis.py
superfluid/src/cfa.py
superfluid/src/constants.py
superfluid/src/errors.py
superfluid/src/host.py
superfluid/src/metadata.py
superfluid/src/operation.py
superfluid/src/types.py
superfluid/src/utils.py
superfluid/test/__init__.py
superfluid/test/test_utils.py
aleph_superfluid-0.3.dist-info/METADATA
aleph_superfluid-0.3.dist-info/WHEEL
aleph_superfluid-0.3.dist-info/top_level.txt
aleph_superfluid-0.3.dist-info/RECORD
