Metadata-Version: 2.4
Name: aleph-superfluid
Version: 0.3
Summary: Fork of the Python SDK for the Superfluid Protocol
Home-page: https://github.com/aleph-im/superfluid.py
Author: Godspower-Eze
Author-email: Godspowereze260@gmail.com
License: MIT
Classifier: License :: OSI Approved :: MIT License
Classifier: Programming Language :: Python :: 3
Classifier: Operating System :: OS Independent
Requires-Python: >=3
License-File: LICENSE.txt
Requires-Dist: web3>=7.10.0
Requires-Dist: python-decouple==3.8
Provides-Extra: dev
Requires-Dist: twine>=4.0.2; extra == "dev"
Dynamic: author
Dynamic: author-email
Dynamic: classifier
Dynamic: description
Dynamic: description-content-type
Dynamic: home-page
Dynamic: license
Dynamic: license-file
Dynamic: provides-extra
Dynamic: requires-dist
Dynamic: requires-python
Dynamic: summary
